.gitignore
LICENSE
Pipfile
Pipfile.lock
README.md
pyproject.toml
pytest.ini
requirements.txt
setup.cfg
setup.py
./croudtech_helm_values_parser/__init__.py
./croudtech_helm_values_parser/cli.py
./croudtech_helm_values_parser/collections.py
./croudtech_helm_values_parser/git_values.py
./croudtech_helm_values_parser/values_parser.py
./croudtech_helm_values_parser.egg-info/PKG-INFO
./croudtech_helm_values_parser.egg-info/SOURCES.txt
./croudtech_helm_values_parser.egg-info/dependency_links.txt
./croudtech_helm_values_parser.egg-info/entry_points.txt
./croudtech_helm_values_parser.egg-info/not-zip-safe
./croudtech_helm_values_parser.egg-info/requires.txt
./croudtech_helm_values_parser.egg-info/top_level.txt
.vscode/settings.json
croudtech_helm_values_parser/__init__.py
croudtech_helm_values_parser/cli.py
croudtech_helm_values_parser/collections.py
croudtech_helm_values_parser/git_values.py
croudtech_helm_values_parser/values_parser.py
croudtech_helm_values_parser/tests/__init__.py
croudtech_helm_values_parser/tests/conftest.py
croudtech_helm_values_parser/tests/test_release.py
croudtech_helm_values_parser/tests/test_release_list.py
test_repo/devops/_openvpn/openvpn.yaml
test_repo/devops/croudtech-simple/adminer.yaml
test_repo/devops/croudtech-simple/beanstalkd-console.yaml
test_repo/devops/croudtech-simple/mongo-express.yaml
test_repo/devops/croudtech-simple/pgadmin.yaml
test_repo/devops/database-replicator/database-replicator.yaml
test_repo/devops/documentation/croudtech-simple/devops-documentation-int.yaml
test_repo/devops/documentation/croudtech-simple/devops-documentation.yaml
test_repo/devops/documentation/oauth2-proxy/devops-documentation-int-oauth2.yaml
test_repo/devops/documentation/oauth2-proxy/devops-documentation-oauth2.yaml
test_repo/devops/foldingathome/fah.yaml
test_repo/devops/jmeter/task-creds-load-test.yaml
test_repo/devops/tools/croudtech-cron/credulator.yaml
test_repo/int/tools/common.yaml
test_repo/int/tools/_croudtech-tools/common.yaml
test_repo/int/tools/croudtech-tools/common.yaml
test_repo/int/tools/croudtech-tools/ppc-healthcheck-extended.yaml
test_repo/int/tools/croudtech-tools/seo-technical-audit.yaml
test_repo/int/tools/rabbitmq-ha/rabbitmq.yaml
test_repo/int/tools/webapp-nuxt/seo-einstein.yaml
test_repo/int/v3/_croudtech-v3-service/common.yaml
test_repo/int/v3/_croudtech-v3-service/system.yaml
