Metadata-Version: 2.1
Name: croudtech-helm-values-parser
Version: 0.0.5
Summary: Helm utilities
Home-page: https://github.com/CroudTech/devops-python-package-deployment-worker
Author: Jim Robinson
Author-email: jscrobinson@gmail.com
License: UNKNOWN
Platform: UNKNOWN
Classifier: Programming Language :: Python :: 3
Classifier: License :: OSI Approved :: MIT License
Classifier: Operating System :: OS Independent
Requires-Python: >=3.6
